dcatoolkit/__init__.py
dcatoolkit/analytics.py
dcatoolkit/representation.py
dcatoolkit-0.2.3.dist-info/licenses/LICENSE
dcatoolkit-0.2.3.dist-info/METADATA
dcatoolkit-0.2.3.dist-info/WHEEL
dcatoolkit-0.2.3.dist-info/top_level.txt
dcatoolkit-0.2.3.dist-info/RECORD
