Metadata-Version: 2.4
Name: dcatoolkit
Version: 0.2.3
Summary: Collection of useful modules and representations for managing DCA output data.
Author-email: Raheel Syed Ahmed <raheelsyedahmed@gmail.com>
Maintainer-email: Raheel Syed Ahmed <raheelsyedahmed@gmail.com>
License: MIT License
Keywords: dca,toolkit,DI,coevolution
Classifier: Development Status :: 4 - Beta
Classifier: Intended Audience :: Science/Research
Classifier: Topic :: Scientific/Engineering :: Bio-Informatics
Classifier: License :: OSI Approved :: MIT License
Classifier: Programming Language :: Python :: 3
Classifier: Programming Language :: Python :: 3.10
Classifier: Programming Language :: Python :: 3.11
Classifier: Programming Language :: Python :: 3.12
Requires-Python: >=3.10
License-File: LICENSE
Requires-Dist: biotite>=1.0.1
Requires-Dist: matplotlib>=3.8.0
Requires-Dist: numpy>=1.26.0
Requires-Dist: pandas>=2.1.0
Requires-Dist: scikit-learn>=1.3
Requires-Dist: scipy>=1.11.0
Provides-Extra: tests
Requires-Dist: pytest; extra == "tests"
Provides-Extra: docs
Requires-Dist: sphinx; extra == "docs"
Requires-Dist: pdoc; extra == "docs"
Requires-Dist: numpydoc; extra == "docs"
Provides-Extra: lint
Requires-Dist: ruffle; extra == "lint"
Dynamic: license-file
